MongoRouter/Executable.py
MongoRouter/MongoProxy.py
MongoRouter/MongoRouter.py
MongoRouter/__init__.py
MongoRouter-0.1.2.dist-info/LICENSE
MongoRouter-0.1.2.dist-info/METADATA
MongoRouter-0.1.2.dist-info/WHEEL
MongoRouter-0.1.2.dist-info/top_level.txt
MongoRouter-0.1.2.dist-info/RECORD
